zoom-us/__init__.py
zoom-us/client.py
zoom-us/util.py
zoom-us/components/__init__.py
zoom-us/components/base.py
zoom-us/components/meeting.py
zoom-us/components/metric.py
zoom-us/components/past_meeting.py
zoom-us/components/phone.py
zoom-us/components/recording.py
zoom-us/components/report.py
zoom-us/components/user.py
zoom-us/components/webinar.py
zoomus/__init__.py
zoomus/client.py
zoomus/util.py
zoomus/components/__init__.py
zoomus/components/base.py
zoomus/components/meeting.py
zoomus/components/metric.py
zoomus/components/past_meeting.py
zoomus/components/phone.py
zoomus/components/recording.py
zoomus/components/report.py
zoomus/components/user.py
zoomus/components/webinar.py
zoom_us-1.1.4.dist-info/LICENSE.txt
zoom_us-1.1.4.dist-info/METADATA
zoom_us-1.1.4.dist-info/WHEEL
zoom_us-1.1.4.dist-info/top_level.txt
zoom_us-1.1.4.dist-info/RECORD
